image_processing_pack/__init__.py
image_processing_pack/processing.py
image_processing_pack/utils.py
processingDIOImage-0.3.dist-info/METADATA
processingDIOImage-0.3.dist-info/WHEEL
processingDIOImage-0.3.dist-info/top_level.txt
processingDIOImage-0.3.dist-info/RECORD
