Metadata-Version: 2.1
Name: processingDIOImage
Version: 0.3
Summary: My short description
Home-page: https://github.com/oliverborba/DIO_Pacotes_Python
Author: Lucas Borba
Author-email: lucas_borba@outlook.com
Requires-Python: >=3.8
